LICENSE
MANIFEST.in
README.rst
runtests.py
setup.py
django_seed/__init__.py
django_seed/exceptions.py
django_seed/guessers.py
django_seed/models.py
django_seed/providers.py
django_seed/seeder.py
django_seed/tests.py
django_seed/toposort.py
django_seed.egg-info/PKG-INFO
django_seed.egg-info/SOURCES.txt
django_seed.egg-info/dependency_links.txt
django_seed.egg-info/not-zip-safe
django_seed.egg-info/requires.txt
django_seed.egg-info/top_level.txt
django_seed/management/__init__.py
django_seed/management/commands/__init__.py
django_seed/management/commands/seed.py